ejtraderNS/__init__.py
ejtraderNS/data/rss.db
ejtraderNS-0.0.3.dist-info/LICENSE
ejtraderNS-0.0.3.dist-info/METADATA
ejtraderNS-0.0.3.dist-info/WHEEL
ejtraderNS-0.0.3.dist-info/top_level.txt
ejtraderNS-0.0.3.dist-info/RECORD
