Metadata-Version: 2.1
Name: ejtraderNS
Version: 0.0.3
Summary: This is a News Library.
Home-page: https://ejtraderNS.readthedocs.io/
Download-URL: https://github.com/ejtraderlabs/ejtraderNS
Author: Emerson Pedroso
Author-email: support@ejtrader.com
License: MIT License
Project-URL: Bug Reports, https://github.com/ejtraderLabs/ejtraderNS/issues
Project-URL: Source, https://github.com/ejtraderLabs/ejtraderNS
Project-URL: Documentation, https://ejtraderNS.readthedocs.io/
Keywords: news,breaknews,historical-data,financial-data,stocks,funds,etfs,indices,currency crosses,bonds,commodities,crypto currencies
Classifier: Programming Language :: Python :: 3 :: Only
Classifier: Programming Language :: Python :: 3.5
Classifier: Programming Language :: Python :: 3.6
Classifier: Programming Language :: Python :: 3.7
Classifier: Programming Language :: Python :: 3.8
Classifier: License :: OSI Approved :: MIT License
Classifier: Intended Audience :: Developers
Classifier: Topic :: Office/Business :: Financial :: Investment
Classifier: Topic :: Scientific/Engineering :: Information Analysis
Classifier: Topic :: Software Development :: Libraries
Requires-Python: >=3
License-File: LICENSE
Requires-Dist: requests
Requires-Dist: feedparser
Requires-Dist: tldextract
